tianqiai/__init__.py
tianqiai/_tianqiai_scripts.py
tianqiai/api_requestor.py
tianqiai/cli.py
tianqiai/error.py
tianqiai/tianqiai_object.py
tianqiai/tianqiai_response.py
tianqiai/upload_progress.py
tianqiai/util.py
tianqiai/validators.py
tianqiai/version.py
tianqiai/api_resources/__init__.py
tianqiai/api_resources/completion.py
tianqiai/api_resources/abstract/__init__.py
tianqiai/api_resources/abstract/api_resource.py
tianqiai/api_resources/abstract/engine_api_resource.py
tianqiai-0.0.2.dist-info/LICENSE
tianqiai-0.0.2.dist-info/METADATA
tianqiai-0.0.2.dist-info/WHEEL
tianqiai-0.0.2.dist-info/entry_points.txt
tianqiai-0.0.2.dist-info/top_level.txt
tianqiai-0.0.2.dist-info/RECORD
